{"is_source_file": true, "format": "TypeScript (Angular component)", "description": "This file defines the root Angular component for a furniture shop application, managing global state like cart count, theming, and global access setup.", "external_files": ["./app.component.html", "./app.component.css", "./config/app-config", "./services/cart.service"], "external_methods": ["getTheme", "inject", "isPlatformBrowser"], "published": ["AppComponent"], "classes": [{"name": "AppComponent", "description": "Angular root component for the application, responsible for theme setup, cart count management, and global accessibility."}], "methods": [{"name": "ngOnInit", "description": "Initializes the component, sets theme styles, and makes the component globally accessible during browser rendering."}, {"name": "getCartCount", "description": "Subscribes to the cart service to update the cart item count signal."}], "calls": ["getTheme()", "inject(PLATFORM_ID)", "inject(CartService)", "isPlatformBrowser(this.platformId)", "this.cartService.getCart().subscribe"], "search-terms": ["Angular AppComponent", "cart count management", "theming", "server-side rendering", "global component access", "signal", "WritableSignal", "SSR-safe DOM access"], "state": 2, "file_id": 6, "knowledge_revision": 120, "git_revision": "9e4f8cc729860fdeca3e13f378935a8202525ed6", "revision_history": [{"29": "3cd6ac42b042f8033dd559495a26cd3759e98b0b"}, {"66": "3cd6ac42b042f8033dd559495a26cd3759e98b0b"}, {"70": "3cd6ac42b042f8033dd559495a26cd3759e98b0b"}, {"76": "3cd6ac42b042f8033dd559495a26cd3759e98b0b"}, {"77": "3cd6ac42b042f8033dd559495a26cd3759e98b0b"}, {"109": "9e4f8cc729860fdeca3e13f378935a8202525ed6"}, {"114": "9e4f8cc729860fdeca3e13f378935a8202525ed6"}, {"115": "9e4f8cc729860fdeca3e13f378935a8202525ed6"}, {"120": "9e4f8cc729860fdeca3e13f378935a8202525ed6"}], "ctags": [{"_type": "tag", "name": "AppComponent", "path": "/home/kavia/workspace/code-generation/furniture-shop-217777-217787/furniture_frontend/src/app/app.component.ts", "pattern": "/^export class AppComponent implements OnInit {$/", "language": "TypeScript", "kind": "class"}, {"_type": "tag", "name": "doc", "path": "/home/kavia/workspace/code-generation/furniture-shop-217777-217787/furniture_frontend/src/app/app.component.ts", "pattern": "/^    const doc = g?.document ?? undefined;$/", "language": "TypeScript", "kind": "constant"}, {"_type": "tag", "name": "g", "path": "/home/kavia/workspace/code-generation/furniture-shop-217777-217787/furniture_frontend/src/app/app.component.ts", "pattern": "/^    const g = typeof globalThis !== 'undefined' ? (globalThis as any) : undefined;$/", "language": "TypeScript", "kind": "constant"}, {"_type": "tag", "name": "platformId", "path": "/home/kavia/workspace/code-generation/furniture-shop-217777-217787/furniture_frontend/src/app/app.component.ts", "pattern": "/^  private platformId = inject(PLATFORM_ID);$/", "language": "TypeScript", "kind": "property", "scope": "AppComponent", "scopeKind": "class"}, {"_type": "tag", "name": "res", "path": "/home/kavia/workspace/code-generation/furniture-shop-217777-217787/furniture_frontend/src/app/app.component.ts", "pattern": "/^        const val = res.items ? res.items.reduce((acc, i) => acc + (i.quantity || 0), 0) : 0;$/", "language": "TypeScript", "kind": "constant"}, {"_type": "tag", "name": "theme", "path": "/home/kavia/workspace/code-generation/furniture-shop-217777-217787/furniture_frontend/src/app/app.component.ts", "pattern": "/^    const theme = getTheme();$/", "language": "TypeScript", "kind": "constant"}, {"_type": "tag", "name": "title", "path": "/home/kavia/workspace/code-generation/furniture-shop-217777-217787/furniture_frontend/src/app/app.component.ts", "pattern": "/^  title = 'Furniture Shop';$/", "language": "TypeScript", "kind": "property", "scope": "AppComponent", "scopeKind": "class"}, {"_type": "tag", "name": "undefined", "path": "/home/kavia/workspace/code-generation/furniture-shop-217777-217787/furniture_frontend/src/app/app.component.ts", "pattern": "/^    const doc = g?.document ?? undefined;$/", "language": "TypeScript", "kind": "constant"}, {"_type": "tag", "name": "val", "path": "/home/kavia/workspace/code-generation/furniture-shop-217777-217787/furniture_frontend/src/app/app.component.ts", "pattern": "/^        const val = res.items ? res.items.reduce((acc, i) => acc + (i.quantity || 0), 0) : 0;$/", "language": "TypeScript", "kind": "constant"}], "hash": "83ecbc597048f05e5e3aa8541b492384", "format-version": 4, "code-base-name": "furniture_frontend", "filename": "furniture_frontend/src/app/app.component.ts", "fields": [{"name": "private platformId = inject(PLATFORM_ID);", "scope": "AppComponent", "scopeKind": "class", "description": "unavailable"}, {"name": "title = 'Furniture Shop';", "scope": "AppComponent", "scopeKind": "class", "description": "unavailable"}]}